{
  "_class": "shapePath",
  "booleanOperation": -1,
  "do_objectID": "6CAA2512-73C2-4427-8422-B6825F2F4593",
  "edited": true,
  "exportOptions": {
    "_class": "exportOptions",
    "exportFormats": [
    ],
    "includedLayerIds": [
    ],
    "layerOptions": 0,
    "shouldTrim": false
  },
  "frame": {
    "_class": "rect",
    "constrainProportions": false,
    "height": 17.999859375,
    "width": 13.99996355918348,
    "x": 0,
    "y": 3.552713678800503e-15
  },
  "isFlippedHorizontal": false,
  "isFlippedVertical": false,
  "isLocked": false,
  "isVisible": true,
  "layerListExpandedType": 0,
  "name": "Path",
  "nameIsFixed": false,
  "path": {
    "_class": "path",
    "isClosed": true,
    "pointRadiusBehaviour": 1,
    "points": [
      {
        "_class": "curvePoint",
        "cornerRadius": 0,
        "curveFrom": "{1.0040651134966121, 0.61068445847233188}",
        "curveMode": 3,
        "curveTo": "{0.87854395344231018, 0.704857069195853}",
        "hasCurveFrom": true,
        "hasCurveTo": true,
        "point": "{0.9878150711991257, 0.62288767880999074}"
      },
      {
        "_class": "curvePoint",
        "cornerRadius": 0,
        "curveFrom": "{0.98779423781156495, 0.57869983359244992}",
        "curveMode": 4,
        "curveTo": "{1.0040651134966121, 0.59090305393010889}",
        "hasCurveFrom": false,
        "hasCurveTo": true,
        "point": "{0.98779423781156495, 0.57869983359244992}"
      },
      {
        "_class": "curvePoint",
        "cornerRadius": 0,
        "curveFrom": "{0.63758499291317194, 0.31601028133032288}",
        "curveMode": 1,
        "curveTo": "{0.63758499291317194, 0.31601028133032288}",
        "hasCurveFrom": false,
        "hasCurveTo": false,
        "point": "{0.63758499291317194, 0.31601028133032288}"
      },
      {
        "_class": "curvePoint",
        "cornerRadius": 0,
        "curveFrom": "{0.69387680610266977, 0.28027562715333709}",
        "curveMode": 4,
        "curveTo": "{0.68704345498270103, 0.27893186665520825}",
        "hasCurveFrom": true,
        "hasCurveTo": false,
        "point": "{0.68704345498270103, 0.27893186665520825}"
      },
      {
        "_class": "curvePoint",
        "cornerRadius": 0,
        "curveFrom": "{0.75439779696702614, 0.28124438472175561}",
        "curveMode": 3,
        "curveTo": "{0.70091849109824711, 0.28124438472175561}",
        "hasCurveFrom": true,
        "hasCurveTo": true,
        "point": "{0.70833517706992044, 0.28124438472175561}"
      },
      {
        "_class": "curvePoint",
        "cornerRadius": 0,
        "curveFrom": "{0.7916687273134404, 0.18422800178126386}",
        "curveMode": 2,
        "curveTo": "{0.7916687273134404, 0.25325979109211788}",
        "hasCurveFrom": true,
        "hasCurveTo": true,
        "point": "{0.7916687273134404, 0.21874389643669084}"
      },
      {
        "_class": "curvePoint",
        "cornerRadius": 0,
        "curveFrom": "{0.66235589072305823, 0.15624340815162613}",
        "curveMode": 2,
        "curveTo": "{0.75439779696702614, 0.15624340815162613}",
        "hasCurveFrom": true,
        "hasCurveTo": true,
        "point": "{0.70833517706992044, 0.15624340815162613}"
      },
      {
        "_class": "curvePoint",
        "cornerRadius": 0,
        "curveFrom": "{0.62500162682640037, 0.22429081477199037}",
        "curveMode": 3,
        "curveTo": "{0.62500162682640037, 0.18422800178126386}",
        "hasCurveFrom": true,
        "hasCurveTo": true,
        "point": "{0.62500162682640037, 0.21874389643669084}"
      },
      {
        "_class": "curvePoint",
        "cornerRadius": 0,
        "curveFrom": "{0.62810580157297147, 0.23472839631559617}",
        "curveMode": 4,
        "curveTo": "{0.62629329685517499, 0.22958773115414957}",
        "hasCurveFrom": false,
        "hasCurveTo": true,
        "point": "{0.62810580157297147, 0.23472839631559617}"
      },
      {
        "_class": "curvePoint",
        "cornerRadius": 0,
        "curveFrom": "{0.57864733950344238, 0.27180681099071086}",
        "curveMode": 1,
        "curveTo": "{0.57864733950344238, 0.27180681099071086}",
        "hasCurveFrom": false,
        "hasCurveTo": false,
        "point": "{0.57864733950344238, 0.27180681099071086}"
      },
      {
        "_class": "curvePoint",
        "cornerRadius": 0,
        "curveFrom": "{0.2122297190826847, -0.0030547113649325389}",
        "curveMode": 4,
        "curveTo": "{0.22847976138017109, 0.0091485089727263505}",
        "hasCurveFrom": true,
        "hasCurveTo": false,
        "point": "{0.22847976138017109, 0.0091485089727263505}"
      },
      {
        "_class": "curvePoint",
        "cornerRadius": 0,
        "curveFrom": "{0.060229323438504116, 0.091086649114446222}",
        "curveMode": 3,
        "curveTo": "{0.18581298365548884, -0.0030390862428612726}",
        "hasCurveFrom": true,
        "hasCurveTo": true,
        "point": "{0.1695837747455633, 0.0091328838506550842}"
      },
      {
        "_class": "curvePoint",
        "cornerRadius": 0,
        "curveFrom": "{0, 0.43193306197704673}",
        "curveMode": 2,
        "curveTo": "{0, 0.20007187556152781}",
        "hasCurveFrom": true,
        "hasCurveTo": true,
        "point": "{0, 0.31599465620825168}"
      },
      {
        "_class": "curvePoint",
        "cornerRadius": 0,
        "curveFrom": "{0.20010468752225252, 0.64582535801060947}",
        "curveMode": 3,
        "curveTo": "{0.060208490050943239, 0.54093391354619969}",
        "hasCurveFrom": true,
        "hasCurveTo": true,
        "point": "{0.16954210797044153, 0.62290330393206195}"
      },
      {
        "_class": "curvePoint",
        "cornerRadius": 0,
        "curveFrom": "{0.26910486712388709, 0.68271627122086898}",
        "curveMode": 4,
        "curveTo": "{0.23352144116990406, 0.66573176352940255}",
        "hasCurveFrom": false,
        "hasCurveTo": true,
        "point": "{0.26910486712388709, 0.68271627122086898}"
      },
      {
        "_class": "curvePoint",
        "cornerRadius": 0,
        "curveFrom": "{0.099250258340032385, 0.93749951171493529}",
        "curveMode": 1,
        "curveTo": "{0.099250258340032385, 0.93749951171493529}",
        "hasCurveFrom": false,
        "hasCurveTo": false,
        "point": "{0.099250258340032385, 0.93749951171493529}"
      },
      {
        "_class": "curvePoint",
        "cornerRadius": 0,
        "curveFrom": "{0.060333490376308516, 0.93749951171493529}",
        "curveMode": 4,
        "curveTo": "{0.083333550243520044, 0.93749951171493529}",
        "hasCurveFrom": true,
        "hasCurveTo": false,
        "point": "{0.083333550243520044, 0.93749951171493529}"
      },
      {
        "_class": "curvePoint",
        "cornerRadius": 0,
        "curveFrom": "{0.041666775121760022, 0.9859998906241455}",
        "curveMode": 2,
        "curveTo": "{0.041666775121760022, 0.95149962109078978}",
        "hasCurveFrom": true,
        "hasCurveTo": true,
        "point": "{0.041666775121760022, 0.96874975585746759}"
      },
      {
        "_class": "curvePoint",
        "cornerRadius": 0,
        "curveFrom": "{0.083333550243520044, 1}",
        "curveMode": 4,
        "curveTo": "{0.060333490376308516, 1}",
        "hasCurveFrom": false,
        "hasCurveTo": true,
        "point": "{0.083333550243520044, 1}"
      },
      {
        "_class": "curvePoint",
        "cornerRadius": 0,
        "curveFrom": "{0.68966846181537189, 1}",
        "curveMode": 4,
        "curveTo": "{0.66666840194816035, 1}",
        "hasCurveFrom": true,
        "hasCurveTo": false,
        "point": "{0.66666840194816035, 1}"
      },
      {
        "_class": "curvePoint",
        "cornerRadius": 0,
        "curveFrom": "{0.70833517706992044, 0.95149962109078978}",
        "curveMode": 2,
        "curveTo": "{0.70833517706992044, 0.9859998906241455}",
        "hasCurveFrom": true,
        "hasCurveTo": true,
        "point": "{0.70833517706992044, 0.96874975585746759}"
      },
      {
        "_class": "curvePoint",
        "cornerRadius": 0,
        "curveFrom": "{0.66666840194816035, 0.93749951171493529}",
        "curveMode": 4,
        "curveTo": "{0.68966846181537189, 0.93749951171493529}",
        "hasCurveFrom": false,
        "hasCurveTo": true,
        "point": "{0.66666840194816035, 0.93749951171493529}"
      },
      {
        "_class": "curvePoint",
        "cornerRadius": 0,
        "curveFrom": "{0.65075169385164811, 0.93749951171493529}",
        "curveMode": 1,
        "curveTo": "{0.65075169385164811, 0.93749951171493529}",
        "hasCurveFrom": false,
        "hasCurveTo": false,
        "point": "{0.65075169385164811, 0.93749951171493529}"
      },
      {
        "_class": "curvePoint",
        "cornerRadius": 0,
        "curveFrom": "{0.54237641175995022, 0.74932616661067664}",
        "curveMode": 4,
        "curveTo": "{0.52445969845759344, 0.74807615684497542}",
        "hasCurveFrom": true,
        "hasCurveTo": false,
        "point": "{0.52445969845759344, 0.74807615684497542}"
      },
      {
        "_class": "curvePoint",
        "cornerRadius": 0,
        "curveFrom": "{0.73323107520517206, 0.74999804685974103}",
        "curveMode": 3,
        "curveTo": "{0.5604389587752332, 0.74999804685974103}",
        "hasCurveFrom": true,
        "hasCurveTo": true,
        "point": "{0.57866817289100325, 0.74999804685974103}"
      }
    ]
  },
  "resizingConstraint": 63,
  "resizingType": 0,
  "rotation": 0,
  "shouldBreakMaskChain": false
}