{
  "_class": "shapePath",
  "booleanOperation": -1,
  "do_objectID": "9CD3A1C7-74CF-4BA9-9581-5DED63F44032",
  "edited": true,
  "exportOptions": {
    "_class": "exportOptions",
    "exportFormats": [
    ],
    "includedLayerIds": [
    ],
    "layerOptions": 0,
    "shouldTrim": false
  },
  "frame": {
    "_class": "rect",
    "constrainProportions": false,
    "height": 14.62505273355104,
    "width": 18,
    "x": 0,
    "y": 0
  },
  "isFlippedHorizontal": false,
  "isFlippedVertical": false,
  "isLocked": false,
  "isVisible": true,
  "layerListExpandedType": 0,
  "name": "Path",
  "nameIsFixed": false,
  "path": {
    "_class": "path",
    "isClosed": true,
    "pointRadiusBehaviour": 1,
    "points": [
      {
        "_class": "curvePoint",
        "cornerRadius": 0,
        "curveFrom": "{0.90625, 0.26924482221495738}",
        "curveMode": 4,
        "curveTo": "{0.95781249999999996, 0.26924482221495738}",
        "hasCurveFrom": false,
        "hasCurveTo": true,
        "point": "{0.90625, 0.26924482221495738}"
      },
      {
        "_class": "curvePoint",
        "cornerRadius": 0,
        "curveFrom": "{0.859375, 0.26924482221495738}",
        "curveMode": 1,
        "curveTo": "{0.859375, 0.26924482221495738}",
        "hasCurveFrom": false,
        "hasCurveTo": false,
        "point": "{0.859375, 0.26924482221495738}"
      },
      {
        "_class": "curvePoint",
        "cornerRadius": 0,
        "curveFrom": "{0.859375, 0.05571046710640179}",
        "curveMode": 4,
        "curveTo": "{0.859375, 0.07694082806099882}",
        "hasCurveFrom": true,
        "hasCurveTo": false,
        "point": "{0.859375, 0.07694082806099882}"
      },
      {
        "_class": "curvePoint",
        "cornerRadius": 0,
        "curveFrom": "{0.828125, 0.038480029230207102}",
        "curveMode": 4,
        "curveTo": "{0.84537499999999999, 0.038480029230207102}",
        "hasCurveFrom": false,
        "hasCurveTo": true,
        "point": "{0.828125, 0.038480029230207102}"
      },
      {
        "_class": "curvePoint",
        "cornerRadius": 0,
        "curveFrom": "{0.56087500000000001, 0.038480029230207102}",
        "curveMode": 4,
        "curveTo": "{0.578125, 0.038480029230207102}",
        "hasCurveFrom": true,
        "hasCurveTo": false,
        "point": "{0.578125, 0.038480029230207102}"
      },
      {
        "_class": "curvePoint",
        "cornerRadius": 0,
        "curveFrom": "{0.546875, 0.07694082806099882}",
        "curveMode": 4,
        "curveTo": "{0.546875, 0.05571046710640179}",
        "hasCurveFrom": false,
        "hasCurveTo": true,
        "point": "{0.546875, 0.07694082806099882}"
      },
      {
        "_class": "curvePoint",
        "cornerRadius": 0,
        "curveFrom": "{0.31087500000000001, 0.07694082806099882}",
        "curveMode": 4,
        "curveTo": "{0.328125, 0.07694082806099882}",
        "hasCurveFrom": true,
        "hasCurveTo": false,
        "point": "{0.328125, 0.07694082806099882}"
      },
      {
        "_class": "curvePoint",
        "cornerRadius": 0,
        "curveFrom": "{0.296875, 0.11540162689179054}",
        "curveMode": 4,
        "curveTo": "{0.296875, 0.094171265937193507}",
        "hasCurveFrom": false,
        "hasCurveTo": true,
        "point": "{0.296875, 0.11540162689179054}"
      },
      {
        "_class": "curvePoint",
        "cornerRadius": 0,
        "curveFrom": "{0.296875, 0.26924482221495738}",
        "curveMode": 1,
        "curveTo": "{0.296875, 0.26924482221495738}",
        "hasCurveFrom": false,
        "hasCurveTo": false,
        "point": "{0.296875, 0.26924482221495738}"
      },
      {
        "_class": "curvePoint",
        "cornerRadius": 0,
        "curveFrom": "{0.20881250000000001, 0.26924482221495738}",
        "curveMode": 1,
        "curveTo": "{0.20881250000000001, 0.26924482221495738}",
        "hasCurveFrom": false,
        "hasCurveTo": false,
        "point": "{0.20881250000000001, 0.26924482221495738}"
      },
      {
        "_class": "curvePoint",
        "cornerRadius": 0,
        "curveFrom": "{0.1875, 0.017249668275610083}",
        "curveMode": 4,
        "curveTo": "{0.1875, 0.038480029230207109}",
        "hasCurveFrom": true,
        "hasCurveTo": false,
        "point": "{0.1875, 0.038480029230207109}"
      },
      {
        "_class": "curvePoint",
        "cornerRadius": 0,
        "curveFrom": "{0.15625, 1.9230399415393741e-05}",
        "curveMode": 4,
        "curveTo": "{0.17351562500000001, 1.9230399415393741e-05}",
        "hasCurveFrom": false,
        "hasCurveTo": true,
        "point": "{0.15625, 1.9230399415393741e-05}"
      },
      {
        "_class": "curvePoint",
        "cornerRadius": 0,
        "curveFrom": "{0.15625, 0}",
        "curveMode": 1,
        "curveTo": "{0.15625, 0}",
        "hasCurveFrom": false,
        "hasCurveTo": false,
        "point": "{0.15625, 0}"
      },
      {
        "_class": "curvePoint",
        "cornerRadius": 0,
        "curveFrom": "{0.031343749999999997, 3.8460798830791718e-05}",
        "curveMode": 4,
        "curveTo": "{0.031390624999999998, 3.8460798830791718e-05}",
        "hasCurveFrom": true,
        "hasCurveTo": false,
        "point": "{0.031390624999999998, 3.8460798830791718e-05}"
      },
      {
        "_class": "curvePoint",
        "cornerRadius": 0,
        "curveFrom": "{0.014, 3.8460798830791718e-05}",
        "curveMode": 3,
        "curveTo": "{0.031296875000000002, 1.9230399415395859e-05}",
        "hasCurveFrom": true,
        "hasCurveTo": true,
        "point": "{0.031234374999999998, 1.9230399415395859e-05}"
      },
      {
        "_class": "curvePoint",
        "cornerRadius": 0,
        "curveFrom": "{0, 0.059729620584219531}",
        "curveMode": 2,
        "curveTo": "{0, 0.017230437876194691}",
        "hasCurveFrom": true,
        "hasCurveTo": true,
        "point": "{0, 0.038480029230207109}"
      },
      {
        "_class": "curvePoint",
        "cornerRadius": 0,
        "curveFrom": "{0.03125, 0.07694082806099882}",
        "curveMode": 4,
        "curveTo": "{0.014, 0.07694082806099882}",
        "hasCurveFrom": false,
        "hasCurveTo": true,
        "point": "{0.03125, 0.07694082806099882}"
      },
      {
        "_class": "curvePoint",
        "cornerRadius": 0,
        "curveFrom": "{0.12587500000000001, 0.07694082806099882}",
        "curveMode": 1,
        "curveTo": "{0.12587500000000001, 0.07694082806099882}",
        "hasCurveFrom": false,
        "hasCurveTo": false,
        "point": "{0.12587500000000001, 0.07694082806099882}"
      },
      {
        "_class": "curvePoint",
        "cornerRadius": 0,
        "curveFrom": "{0.203125, 0.94807792157843118}",
        "curveMode": 4,
        "curveTo": "{0.203125, 0.88461760350762486}",
        "hasCurveFrom": true,
        "hasCurveTo": false,
        "point": "{0.203125, 0.88461760350762486}"
      },
      {
        "_class": "curvePoint",
        "cornerRadius": 0,
        "curveFrom": "{0.296875, 1}",
        "curveMode": 4,
        "curveTo": "{0.24531249999999999, 1}",
        "hasCurveFrom": false,
        "hasCurveTo": true,
        "point": "{0.296875, 1}"
      },
      {
        "_class": "curvePoint",
        "cornerRadius": 0,
        "curveFrom": "{0.91093749999999996, 1}",
        "curveMode": 4,
        "curveTo": "{0.859375, 1}",
        "hasCurveFrom": true,
        "hasCurveTo": false,
        "point": "{0.859375, 1}"
      },
      {
        "_class": "curvePoint",
        "cornerRadius": 0,
        "curveFrom": "{0.953125, 0.88461760350762486}",
        "curveMode": 4,
        "curveTo": "{0.953125, 0.94807792157843118}",
        "hasCurveFrom": false,
        "hasCurveTo": true,
        "point": "{0.953125, 0.88461760350762486}"
      },
      {
        "_class": "curvePoint",
        "cornerRadius": 0,
        "curveFrom": "{1, 0.3211669006365262}",
        "curveMode": 4,
        "curveTo": "{1, 0.38462721870733252}",
        "hasCurveFrom": true,
        "hasCurveTo": false,
        "point": "{1, 0.38462721870733252}"
      }
    ]
  },
  "resizingConstraint": 63,
  "resizingType": 0,
  "rotation": 0,
  "shouldBreakMaskChain": false
}