{
  "_class": "shapeGroup",
  "clippingMaskMode": 0,
  "do_objectID": "1705B9E2-B045-4F8A-A720-3FB5D1277B95",
  "exportOptions": {
    "_class": "exportOptions",
    "exportFormats": [
    ],
    "includedLayerIds": [
    ],
    "layerOptions": 0,
    "shouldTrim": false
  },
  "frame": {
    "_class": "rect",
    "constrainProportions": true,
    "height": 18,
    "width": 18,
    "x": 3,
    "y": 3
  },
  "hasClickThrough": false,
  "hasClippingMask": true,
  "isFlippedHorizontal": false,
  "isFlippedVertical": false,
  "isLocked": false,
  "isVisible": true,
  "layerListExpandedType": 0,
  "layers": [
    {
      "class": "shapePath",
      "id": "0FE13442-A17B-40A1-A665-DE158A246FF8"
    },
    {
      "class": "shapePath",
      "id": "20D2AEA4-87BE-4A43-8B9B-5A1E5FA605A4"
    },
    {
      "class": "shapePath",
      "id": "571483F4-6E0E-432A-ABB4-0C4FFA92C903"
    },
    {
      "class": "shapePath",
      "id": "2C3B322C-634D-441A-AC1A-057297C6E84D"
    },
    {
      "class": "shapePath",
      "id": "F45FE8CC-7A2E-4462-82A3-FDE5BF7EDE32"
    },
    {
      "class": "shapePath",
      "id": "6BB43409-3A13-4AD4-885F-33B12CB1EBD9"
    },
    {
      "class": "shapePath",
      "id": "E1A6FBF7-A16F-4C5F-ACCC-AD557914614F"
    }
  ],
  "name": "sale",
  "nameIsFixed": false,
  "resizingConstraint": 63,
  "resizingType": 0,
  "rotation": 0,
  "shouldBreakMaskChain": false,
  "style": {
    "_class": "style",
    "endDecorationType": 0,
    "fills": [
      {
        "_class": "fill",
        "color": {
          "_class": "color",
          "alpha": 1,
          "blue": 0,
          "green": 0,
          "red": 0
        },
        "fillType": 0,
        "isEnabled": true,
        "noiseIndex": 0,
        "noiseIntensity": 0,
        "patternFillType": 1,
        "patternTileScale": 1
      }
    ],
    "miterLimit": 10,
    "startDecorationType": 0
  },
  "windingRule": 0
}