{
  "_class": "shapePath",
  "booleanOperation": -1,
  "do_objectID": "F99A894E-D485-40BF-8170-886EC79EEEBB",
  "edited": true,
  "exportOptions": {
    "_class": "exportOptions",
    "exportFormats": [
    ],
    "includedLayerIds": [
    ],
    "layerOptions": 0,
    "shouldTrim": false
  },
  "frame": {
    "_class": "rect",
    "constrainProportions": false,
    "height": 5.939699999999999,
    "width": 5.568187500000001,
    "x": 11.30666196558463,
    "y": 1.2
  },
  "isFlippedHorizontal": false,
  "isFlippedVertical": false,
  "isLocked": false,
  "isVisible": true,
  "layerListExpandedType": 0,
  "name": "Path",
  "nameIsFixed": false,
  "path": {
    "_class": "path",
    "isClosed": true,
    "pointRadiusBehaviour": 1,
    "points": [
      {
        "_class": "curvePoint",
        "cornerRadius": 0,
        "curveFrom": "{0.59591877967471463, 1}",
        "curveMode": 4,
        "curveTo": "{0.82624507526012747, 0.95302793070357095}",
        "hasCurveFrom": false,
        "hasCurveTo": true,
        "point": "{0.59591877967471463, 1}"
      },
      {
        "_class": "curvePoint",
        "cornerRadius": 0,
        "curveFrom": "{0.59591877967471463, 0.44931562200111119}",
        "curveMode": 4,
        "curveTo": "{0.59591877967471463, 0.50507601394009805}",
        "hasCurveFrom": true,
        "hasCurveTo": false,
        "point": "{0.59591877967471463, 0.50507601394009805}"
      },
      {
        "_class": "curvePoint",
        "cornerRadius": 0,
        "curveFrom": "{0.49489847459339331, 0.40406081115207843}",
        "curveMode": 4,
        "curveTo": "{0.55066168299828266, 0.40406081115207843}",
        "hasCurveFrom": false,
        "hasCurveTo": true,
        "point": "{0.49489847459339331, 0.40406081115207843}"
      },
      {
        "_class": "curvePoint",
        "cornerRadius": 0,
        "curveFrom": "{0.046923931710273863, 0.17379665639678771}",
        "curveMode": 4,
        "curveTo": "{0, 0.40406081115207843}",
        "hasCurveFrom": true,
        "hasCurveTo": false,
        "point": "{0, 0.40406081115207843}"
      },
      {
        "_class": "curvePoint",
        "cornerRadius": 0,
        "curveFrom": "{0.77346196585513693, 0}",
        "curveMode": 3,
        "curveTo": "{0.2509849479745429, 0}",
        "hasCurveFrom": true,
        "hasCurveTo": true,
        "point": "{0.49489847459339331, 0}"
      },
      {
        "_class": "curvePoint",
        "cornerRadius": 0,
        "curveFrom": "{1, 0.74897722107177134}",
        "curveMode": 3,
        "curveTo": "{1, 0.226577099853528}",
        "hasCurveFrom": true,
        "hasCurveTo": true,
        "point": "{1, 0.50507601394009805}"
      }
    ]
  },
  "resizingConstraint": 63,
  "resizingType": 0,
  "rotation": 0,
  "shouldBreakMaskChain": false
}