{
  "_class": "shapePath",
  "booleanOperation": -1,
  "do_objectID": "2C78E527-6AE7-48C6-BE40-72C13456B3BA",
  "edited": true,
  "exportOptions": {
    "_class": "exportOptions",
    "exportFormats": [
    ],
    "includedLayerIds": [
    ],
    "layerOptions": 0,
    "shouldTrim": false
  },
  "frame": {
    "_class": "rect",
    "constrainProportions": false,
    "height": 3.2124375,
    "width": 4.539339424950933,
    "x": 10.00135863388627,
    "y": 7.193812499999995
  },
  "isFlippedHorizontal": false,
  "isFlippedVertical": false,
  "isLocked": false,
  "isVisible": true,
  "layerListExpandedType": 0,
  "name": "Path",
  "nameIsFixed": false,
  "path": {
    "_class": "path",
    "isClosed": true,
    "pointRadiusBehaviour": 1,
    "points": [
      {
        "_class": "curvePoint",
        "cornerRadius": 0,
        "curveFrom": "{0.71846344485749669, 0.62764839782875159}",
        "curveMode": 4,
        "curveTo": "{0.73717472118959082, 0.50271406058483636}",
        "hasCurveFrom": true,
        "hasCurveTo": false,
        "point": "{0.73717472118959082, 0.50271406058483636}"
      },
      {
        "_class": "curvePoint",
        "cornerRadius": 0,
        "curveFrom": "{0.69919454770755862, 0.72684293468744554}",
        "curveMode": 4,
        "curveTo": "{0.70700123915737256, 0.71546139029942213}",
        "hasCurveFrom": true,
        "hasCurveTo": true,
        "point": "{0.7027881040892191, 0.76606548765540217}"
      },
      {
        "_class": "curvePoint",
        "cornerRadius": 0,
        "curveFrom": "{0.67081784386617038, 0.50893013482752636}",
        "curveMode": 2,
        "curveTo": "{0.69213135068153653, 0.66757135352827901}",
        "hasCurveFrom": true,
        "hasCurveTo": true,
        "point": "{0.68147459727385351, 0.58825074417790268}"
      },
      {
        "_class": "curvePoint",
        "cornerRadius": 0,
        "curveFrom": "{0.64999999999999947, 0.37830502538959943}",
        "curveMode": 4,
        "curveTo": "{0.66034696406443583, 0.43888986167046096}",
        "hasCurveFrom": false,
        "hasCurveTo": true,
        "point": "{0.64999999999999947, 0.37830502538959943}"
      },
      {
        "_class": "curvePoint",
        "cornerRadius": 0,
        "curveFrom": "{0.5894671623296156, 8.7550341446749672e-05}",
        "curveMode": 1,
        "curveTo": "{0.5894671623296156, 8.7550341446749672e-05}",
        "hasCurveFrom": false,
        "hasCurveTo": false,
        "point": "{0.5894671623296156, 8.7550341446749672e-05}"
      },
      {
        "_class": "curvePoint",
        "cornerRadius": 0,
        "curveFrom": "{0.41232961586121397, 8.7550341446749672e-05}",
        "curveMode": 1,
        "curveTo": "{0.41232961586121397, 8.7550341446749672e-05}",
        "hasCurveFrom": false,
        "hasCurveTo": false,
        "point": "{0.41232961586121397, 8.7550341446749672e-05}"
      },
      {
        "_class": "curvePoint",
        "cornerRadius": 0,
        "curveFrom": "{0.3405204460966535, 0.43074767991595209}",
        "curveMode": 4,
        "curveTo": "{0.34987608426270084, 0.37830502538959943}",
        "hasCurveFrom": true,
        "hasCurveTo": false,
        "point": "{0.34987608426270084, 0.37830502538959943}"
      },
      {
        "_class": "curvePoint",
        "cornerRadius": 0,
        "curveFrom": "{0.30879801734820289, 0.65654001050604205}",
        "curveMode": 2,
        "curveTo": "{0.33048327137546402, 0.49684818770793243}",
        "hasCurveFrom": true,
        "hasCurveTo": true,
        "point": "{0.31964064436183343, 0.5766940991069871}"
      },
      {
        "_class": "curvePoint",
        "cornerRadius": 0,
        "curveFrom": "{0.2907063197026018, 0.70049028191210017}",
        "curveMode": 4,
        "curveTo": "{0.30130111524163522, 0.71966380668884689}",
        "hasCurveFrom": true,
        "hasCurveTo": true,
        "point": "{0.29714993804213086, 0.76615303799684886}"
      },
      {
        "_class": "curvePoint",
        "cornerRadius": 0,
        "curveFrom": "{0.2613382899628246, 0.50148835580458839}",
        "curveMode": 4,
        "curveTo": "{0.27874845105328344, 0.61223953773419759}",
        "hasCurveFrom": false,
        "hasCurveTo": true,
        "point": "{0.2613382899628246, 0.50148835580458839}"
      },
      {
        "_class": "curvePoint",
        "cornerRadius": 0,
        "curveFrom": "{0.18438661710037124, 8.7550341447060716e-05}",
        "curveMode": 1,
        "curveTo": "{0.18438661710037124, 8.7550341447060716e-05}",
        "hasCurveFrom": false,
        "hasCurveTo": false,
        "point": "{0.18438661710037124, 8.7550341447060716e-05}"
      },
      {
        "_class": "curvePoint",
        "cornerRadius": 0,
        "curveFrom": "{0, 8.7550341447060716e-05}",
        "curveMode": 1,
        "curveTo": "{0, 8.7550341447060716e-05}",
        "hasCurveFrom": false,
        "hasCurveTo": false,
        "point": "{0, 8.7550341447060716e-05}"
      },
      {
        "_class": "curvePoint",
        "cornerRadius": 0,
        "curveFrom": "{0.17521685254027236, 1}",
        "curveMode": 1,
        "curveTo": "{0.17521685254027236, 1}",
        "hasCurveFrom": false,
        "hasCurveTo": false,
        "point": "{0.17521685254027236, 1}"
      },
      {
        "_class": "curvePoint",
        "cornerRadius": 0,
        "curveFrom": "{0.44256505576208183, 0.73778672736823703}",
        "curveMode": 4,
        "curveTo": "{0.40123915737298632, 1}",
        "hasCurveFrom": true,
        "hasCurveTo": false,
        "point": "{0.40123915737298632, 1}"
      },
      {
        "_class": "curvePoint",
        "cornerRadius": 0,
        "curveFrom": "{0.47732342007434947, 0.51435825599719864}",
        "curveMode": 2,
        "curveTo": "{0.46604708798017336, 0.58825074417790202}",
        "hasCurveFrom": true,
        "hasCurveTo": true,
        "point": "{0.47168525402726141, 0.55130450008755039}"
      },
      {
        "_class": "curvePoint",
        "cornerRadius": 0,
        "curveFrom": "{0.4946096654275095, 0.38583435475398353}",
        "curveMode": 2,
        "curveTo": "{0.48308550185873583, 0.47390999824899316}",
        "hasCurveFrom": true,
        "hasCurveTo": true,
        "point": "{0.4888475836431227, 0.42987217650148835}"
      },
      {
        "_class": "curvePoint",
        "cornerRadius": 0,
        "curveFrom": "{0.50464684014869909, 0.35589213797933822}",
        "curveMode": 4,
        "curveTo": "{0.49882280049566308, 0.34906321134652407}",
        "hasCurveFrom": true,
        "hasCurveTo": true,
        "point": "{0.50142503097893454, 0.31938364559621779}"
      },
      {
        "_class": "curvePoint",
        "cornerRadius": 0,
        "curveFrom": "{0.52360594795539084, 0.5098056382419891}",
        "curveMode": 2,
        "curveTo": "{0.50972738537794327, 0.40124321484853775}",
        "hasCurveFrom": true,
        "hasCurveTo": true,
        "point": "{0.51666666666666705, 0.45552442654526343}"
      },
      {
        "_class": "curvePoint",
        "cornerRadius": 0,
        "curveFrom": "{0.53190830235439945, 0.56426195062160711}",
        "curveMode": 4,
        "curveTo": "{0.5286864931846349, 0.54605147960077027}",
        "hasCurveFrom": false,
        "hasCurveTo": true,
        "point": "{0.53190830235439945, 0.56426195062160711}"
      },
      {
        "_class": "curvePoint",
        "cornerRadius": 0,
        "curveFrom": "{0.5996902106567531, 1}",
        "curveMode": 1,
        "curveTo": "{0.5996902106567531, 1}",
        "hasCurveFrom": false,
        "hasCurveTo": false,
        "point": "{0.5996902106567531, 1}"
      },
      {
        "_class": "curvePoint",
        "cornerRadius": 0,
        "curveFrom": "{0.825712515489467, 1}",
        "curveMode": 1,
        "curveTo": "{0.825712515489467, 1}",
        "hasCurveFrom": false,
        "hasCurveTo": false,
        "point": "{0.825712515489467, 1}"
      },
      {
        "_class": "curvePoint",
        "cornerRadius": 0,
        "curveFrom": "{1, 0}",
        "curveMode": 1,
        "curveTo": "{1, 0}",
        "hasCurveFrom": false,
        "hasCurveTo": false,
        "point": "{1, 0}"
      },
      {
        "_class": "curvePoint",
        "cornerRadius": 0,
        "curveFrom": "{0.8155514250309791, 0}",
        "curveMode": 1,
        "curveTo": "{0.8155514250309791, 0}",
        "hasCurveFrom": false,
        "hasCurveTo": false,
        "point": "{0.8155514250309791, 0}"
      },
      {
        "_class": "curvePoint",
        "cornerRadius": 0,
        "curveFrom": "{0.73717472118959126, 0.50271406058483636}",
        "curveMode": 1,
        "curveTo": "{0.73717472118959126, 0.50271406058483636}",
        "hasCurveFrom": false,
        "hasCurveTo": false,
        "point": "{0.73717472118959126, 0.50271406058483636}"
      }
    ]
  },
  "resizingConstraint": 63,
  "resizingType": 0,
  "rotation": 0,
  "shouldBreakMaskChain": false
}