{
  "_class": "shapeGroup",
  "clippingMaskMode": 0,
  "do_objectID": "B2B6CA4E-4411-48D9-91D8-E6DC25ABD36E",
  "exportOptions": {
    "_class": "exportOptions",
    "exportFormats": [
    ],
    "includedLayerIds": [
    ],
    "layerOptions": 0,
    "shouldTrim": false
  },
  "frame": {
    "_class": "rect",
    "constrainProportions": true,
    "height": 18,
    "width": 18,
    "x": 3,
    "y": 3
  },
  "hasClickThrough": false,
  "hasClippingMask": true,
  "isFlippedHorizontal": false,
  "isFlippedVertical": false,
  "isLocked": false,
  "isVisible": true,
  "layerListExpandedType": 0,
  "layers": [
    {
      "class": "shapePath",
      "id": "93F7F08D-0669-4025-AF30-94EDE0607AFC"
    },
    {
      "class": "shapePath",
      "id": "68B2327A-E3B8-4C53-A9EE-56354BD36A9C"
    },
    {
      "class": "shapePath",
      "id": "EC7AAD38-4529-4418-A2B7-26D75C1EA32A"
    },
    {
      "class": "shapePath",
      "id": "621F26DD-43CE-4FAD-A14B-2058F9760861"
    },
    {
      "class": "shapePath",
      "id": "7F0C3D42-DBF9-41BD-A73B-98AA349FE11A"
    },
    {
      "class": "shapePath",
      "id": "9591505A-AB43-4CE7-ACEB-BD05E0B6D8E6"
    },
    {
      "class": "shapePath",
      "id": "4BBB30BA-4C1F-44E9-BECB-36069BA46E71"
    },
    {
      "class": "shapePath",
      "id": "F441B4BC-801D-4409-BC50-543AC1C5283B"
    }
  ],
  "name": "photocamera_light",
  "nameIsFixed": false,
  "resizingConstraint": 63,
  "resizingType": 0,
  "rotation": 0,
  "shouldBreakMaskChain": false,
  "style": {
    "_class": "style",
    "endDecorationType": 0,
    "fills": [
      {
        "_class": "fill",
        "color": {
          "_class": "color",
          "alpha": 1,
          "blue": 0,
          "green": 0,
          "red": 0
        },
        "fillType": 0,
        "isEnabled": true,
        "noiseIndex": 0,
        "noiseIntensity": 0,
        "patternFillType": 1,
        "patternTileScale": 1
      }
    ],
    "miterLimit": 10,
    "startDecorationType": 0
  },
  "windingRule": 0
}