{
  "_class": "shapeGroup",
  "clippingMaskMode": 0,
  "do_objectID": "DE73CB61-BED5-47F2-94BA-D3D33264D2AE",
  "exportOptions": {
    "_class": "exportOptions",
    "exportFormats": [
    ],
    "includedLayerIds": [
    ],
    "layerOptions": 0,
    "shouldTrim": false
  },
  "frame": {
    "_class": "rect",
    "constrainProportions": true,
    "height": 15,
    "width": 18,
    "x": 3,
    "y": 4.5
  },
  "hasClickThrough": false,
  "hasClippingMask": true,
  "isFlippedHorizontal": false,
  "isFlippedVertical": false,
  "isLocked": false,
  "isVisible": true,
  "layerListExpandedType": 0,
  "layers": [
    {
      "class": "shapePath",
      "id": "DF9803D6-A57D-49C3-A108-727A2DC15A2E"
    },
    {
      "class": "shapePath",
      "id": "60B7F7E5-76E1-4CC7-A9CA-B195BF5576B6"
    },
    {
      "class": "shapePath",
      "id": "74C843C9-B099-47F9-87AB-22DDBE4D7FA0"
    },
    {
      "class": "shapePath",
      "id": "0BF76CA0-AD84-43FB-BF0F-B412ACB7835E"
    },
    {
      "class": "shapePath",
      "id": "786D5380-9133-4867-BF6B-0BC7304CEB47"
    },
    {
      "class": "shapePath",
      "id": "F97063AA-719E-46C9-9C45-46DDBD0D5ADF"
    },
    {
      "class": "shapePath",
      "id": "DCBE740B-6629-48C2-A6BD-B22D00275EB9"
    },
    {
      "class": "shapePath",
      "id": "83A1C235-6851-4EC3-8A54-831CDAD8ACE3"
    }
  ],
  "name": "banknotes",
  "nameIsFixed": false,
  "resizingConstraint": 63,
  "resizingType": 0,
  "rotation": 0,
  "shouldBreakMaskChain": false,
  "style": {
    "_class": "style",
    "endDecorationType": 0,
    "fills": [
      {
        "_class": "fill",
        "color": {
          "_class": "color",
          "alpha": 1,
          "blue": 0,
          "green": 0,
          "red": 0
        },
        "fillType": 0,
        "isEnabled": true,
        "noiseIndex": 0,
        "noiseIntensity": 0,
        "patternFillType": 1,
        "patternTileScale": 1
      }
    ],
    "miterLimit": 10,
    "startDecorationType": 0
  },
  "windingRule": 0
}