{
  "_class": "shapePath",
  "booleanOperation": -1,
  "do_objectID": "964397B0-4F79-45B2-BD69-827106CEEFFB",
  "edited": true,
  "exportOptions": {
    "_class": "exportOptions",
    "exportFormats": [
    ],
    "includedLayerIds": [
    ],
    "layerOptions": 0,
    "shouldTrim": false
  },
  "frame": {
    "_class": "rect",
    "constrainProportions": false,
    "height": 14.06371375768546,
    "width": 17.99971875,
    "x": 1.77635683940025e-15,
    "y": 0
  },
  "isFlippedHorizontal": false,
  "isFlippedVertical": false,
  "isLocked": false,
  "isVisible": true,
  "layerListExpandedType": 0,
  "name": "Path",
  "nameIsFixed": false,
  "path": {
    "_class": "path",
    "isClosed": true,
    "pointRadiusBehaviour": 1,
    "points": [
      {
        "_class": "curvePoint",
        "cornerRadius": 0,
        "curveFrom": "{1, 0.59123528116046487}",
        "curveMode": 2,
        "curveTo": "{1, 0.66648878590572758}",
        "hasCurveFrom": true,
        "hasCurveTo": true,
        "point": "{1, 0.63003193255717216}"
      },
      {
        "_class": "curvePoint",
        "cornerRadius": 0,
        "curveFrom": "{0.92915514304911007, 0.40617125434338758}",
        "curveMode": 4,
        "curveTo": "{0.98274973046453851, 0.55837811711675855}",
        "hasCurveFrom": true,
        "hasCurveTo": true,
        "point": "{0.95879623119111235, 0.54577920454978657}"
      },
      {
        "_class": "curvePoint",
        "cornerRadius": 0,
        "curveFrom": "{0.79699682807543859, 0.21032815788567877}",
        "curveMode": 4,
        "curveTo": "{0.8354974296473382, 0.29996042157642222}",
        "hasCurveFrom": true,
        "hasCurveTo": true,
        "point": "{0.72079251238300601, 0.2825419249957356}"
      },
      {
        "_class": "curvePoint",
        "cornerRadius": 0,
        "curveFrom": "{0.81627837934967717, 0.043542553427668884}",
        "curveMode": 3,
        "curveTo": "{0.84601321895654613, 0.12567546439997659}",
        "hasCurveFrom": true,
        "hasCurveTo": true,
        "point": "{0.82193471772996451, 0.059141207082015125}"
      },
      {
        "_class": "curvePoint",
        "cornerRadius": 0,
        "curveFrom": "{0.71958936858388423, -0.016052302841500148}",
        "curveMode": 3,
        "curveTo": "{0.80391881123142539, 0.022364381350806449}",
        "hasCurveFrom": true,
        "hasCurveTo": true,
        "point": "{0.77710589227956695, 0.010165434262151055}"
      },
      {
        "_class": "curvePoint",
        "cornerRadius": 0,
        "curveFrom": "{0.40945952280504377, 0.13887432518442344}",
        "curveMode": 2,
        "curveTo": "{0.61716589321708148, 0.0093055084837704253}",
        "hasCurveFrom": true,
        "hasCurveTo": true,
        "point": "{0.50978921545649147, 0.076279727827880159}"
      },
      {
        "_class": "curvePoint",
        "cornerRadius": 0,
        "curveFrom": "{0.30780168440131878, 0.24020557911592666}",
        "curveMode": 4,
        "curveTo": "{0.3462241597524961, 0.19166976832221075}",
        "hasCurveFrom": true,
        "hasCurveTo": true,
        "point": "{0.31342677229331706, 0.24054554977249573}"
      },
      {
        "_class": "curvePoint",
        "cornerRadius": 0,
        "curveFrom": "{0.1415022109720464, 0.24006559119851584}",
        "curveMode": 3,
        "curveTo": "{0.30234847419490929, 0.24006559119851584}",
        "hasCurveFrom": true,
        "hasCurveTo": true,
        "point": "{0.29687963874435536, 0.24006559119851584}"
      },
      {
        "_class": "curvePoint",
        "cornerRadius": 0,
        "curveFrom": "{0, 0.63505149931004512}",
        "curveMode": 3,
        "curveTo": "{0, 0.40211160473847446}",
        "hasCurveFrom": true,
        "hasCurveTo": true,
        "point": "{0, 0.58003624776760088}"
      },
      {
        "_class": "curvePoint",
        "cornerRadius": 0,
        "curveFrom": "{0.082407537617775264, 0.74716182288217992}",
        "curveMode": 3,
        "curveTo": "{0.021453460210315783, 0.68758696488692672}",
        "hasCurveFrom": true,
        "hasCurveTo": true,
        "point": "{0.058875919936248994, 0.72416380787897705}"
      },
      {
        "_class": "curvePoint",
        "cornerRadius": 0,
        "curveFrom": "{0.18150283598181222, 0.81465599734810112}",
        "curveMode": 4,
        "curveTo": "{0.12672073001140641, 0.77757919750815507}",
        "hasCurveFrom": true,
        "hasCurveTo": true,
        "point": "{0.19687807621994094, 0.77823914054737742}"
      },
      {
        "_class": "curvePoint",
        "cornerRadius": 0,
        "curveFrom": "{0.17187768558883731, 0.95514387160679659}",
        "curveMode": 3,
        "curveTo": "{0.17187768558883731, 0.8574923000758059}",
        "hasCurveFrom": true,
        "hasCurveTo": true,
        "point": "{0.17187768558883731, 0.90000863042085733}"
      },
      {
        "_class": "curvePoint",
        "cornerRadius": 0,
        "curveFrom": "{0.25000390631103614, 1}",
        "curveMode": 4,
        "curveTo": "{0.20692510820481572, 1}",
        "hasCurveFrom": false,
        "hasCurveTo": true,
        "point": "{0.25000390631103614, 1}"
      },
      {
        "_class": "curvePoint",
        "cornerRadius": 0,
        "curveFrom": "{0.82335661494710843, 1}",
        "curveMode": 4,
        "curveTo": "{0.68751074235534915, 1}",
        "hasCurveFrom": true,
        "hasCurveTo": false,
        "point": "{0.68751074235534915, 1}"
      },
      {
        "_class": "curvePoint",
        "cornerRadius": 0,
        "curveFrom": "{0.98479663744746015, 0.69780608285791501}",
        "curveMode": 4,
        "curveTo": "{0.93699901560961874, 0.87609069481752644}",
        "hasCurveFrom": true,
        "hasCurveTo": true,
        "point": "{0.96310879857497766, 0.71194486251640576}"
      }
    ]
  },
  "resizingConstraint": 63,
  "resizingType": 0,
  "rotation": 0,
  "shouldBreakMaskChain": false
}